{"cameraMode":{"drawMode":0,"name":"Shaded","section":"Shading Mode"},"sceneLighting":false,"audioPlay":false,"sceneViewState":{"m_AlwaysRefresh":false,"showFog":true,"showSkybox":false,"showFlares":true,"showImageEffects":true,"showParticleSystems":true,"showVisualEffectGraphs":true,"m_FxEnabled":false},"in2DMode":false,"pivot":{"x":-3.948434591293335,"y":-3.3653976917266847,"z":-5.772202014923096},"rotation":{"x":-0.06579176336526871,"y":0.934106707572937,"z":-0.24081675708293916,"w":-0.25520557165145876},"size":8.938922882080079,"orthographic":false}